api_name/__init__.py
api_name/api.py
api_name/config.cfg
api_name-1.0.0.dist-info/LICENSE
api_name-1.0.0.dist-info/METADATA
api_name-1.0.0.dist-info/WHEEL
api_name-1.0.0.dist-info/top_level.txt
api_name-1.0.0.dist-info/RECORD
