Metadata-Version: 2.1
Name: api-name
Version: 1.0.0
Summary: Read the latest Real Python tutorials
Home-page: https://github.com/ll/api_name
Author: ll
Author-email: info@realpython.com
License: MIT
Platform: UNKNOWN
Classifier: License :: OSI Approved :: MIT License
Classifier: Programming Language :: Python
Classifier: Programming Language :: Python :: 3
